benchmarks/__init__.py
benchmarks/test_dmet_classical.py
benchmarks/test_dmet_problem_decomposition_microsoft_qsharp.py
benchmarks/test_vqe_solver_microsoft_qsharp.py
openqemist/__init__.py
openqemist/electronic_structure_solvers/__init__.py
openqemist/electronic_structure_solvers/electronic_structure_solver.py
openqemist/electronic_structure_solvers/ccsd_solver/__init__.py
openqemist/electronic_structure_solvers/ccsd_solver/ccsd_solver.py
openqemist/electronic_structure_solvers/fci_solver/__init__.py
openqemist/electronic_structure_solvers/fci_solver/fci_solver.py
openqemist/electronic_structure_solvers/vqe_solver/__init__.py
openqemist/electronic_structure_solvers/vqe_solver/vqe_solver.py
openqemist/problem_decomposition/__init__.py
openqemist/problem_decomposition/problem_decomposition.py
openqemist/problem_decomposition/dmet/__init__.py
openqemist/problem_decomposition/dmet/dmet_problem_decomposition.py
openqemist/problem_decomposition/dmet/_helpers/__init__.py
openqemist/problem_decomposition/dmet/_helpers/dmet_bath.py
openqemist/problem_decomposition/dmet/_helpers/dmet_fragment.py
openqemist/problem_decomposition/dmet/_helpers/dmet_onerdm.py
openqemist/problem_decomposition/dmet/_helpers/dmet_oneshot_loop.py
openqemist/problem_decomposition/dmet/_helpers/dmet_orbitals.py
openqemist/problem_decomposition/dmet/_helpers/dmet_scf.py
openqemist/problem_decomposition/dmet/_helpers/dmet_scf_guess.py
openqemist/problem_decomposition/electron_localization/__init__.py
openqemist/problem_decomposition/electron_localization/iao_localization.py
openqemist/problem_decomposition/electron_localization/meta_lowdin_localization.py
openqemist/quantum_solvers/__init__.py
openqemist/quantum_solvers/_variational_parameters.py
openqemist/quantum_solvers/initial_parameters.py
openqemist/quantum_solvers/parametric_quantum_solver.py
openqemist/quantum_solvers/microsoft_qsharp/__init__.py
openqemist/quantum_solvers/microsoft_qsharp/broombridge_dummy.py
openqemist-0.2.1.dist-info/LICENSE
openqemist-0.2.1.dist-info/METADATA
openqemist-0.2.1.dist-info/WHEEL
openqemist-0.2.1.dist-info/top_level.txt
openqemist-0.2.1.dist-info/RECORD
