Metadata-Version: 2.1
Name: openqemist
Version: 0.2.1
Summary: Quantum chemistry simulation library.
Home-page: https://github.com/1QB-Information-Technologies/openqemist
Author: Rudi Plesch
Author-email: rudi.plesch@1qbit.com
License: UNKNOWN
Platform: UNKNOWN
Classifier: Programming Language :: Python :: 3
Classifier: Operating System :: OS Independent
Classifier: License :: OSI Approved :: Apache Software License
Requires-Dist: pyscf (==1.6)
Requires-Dist: numpy
Requires-Dist: scipy
Requires-Dist: qsharp
Requires-Dist: qiskit (==0.13)
Requires-Dist: pyquil
Requires-Dist: forestopenfermion
